cornichon/__init__.py
cornichon/common.py
cornichon/cornichon.py
cornichon/gherkin.py
cornichon/cpp/cppscenarios.py
cornichon/cpp/cppunittest.py
cornichon/cpp/cpputils.py
cornichon/cpp/googletest.py
cornichon/cs/csscenarios.py
cornichon/cs/csutils.py
cornichon/cs/nunit.py
cornichon/cs/unittesting.py
cornichon/py/pyscenarios.py
cornichon/py/pytests.py
cornichon/py/pyunit_tests.py
cornichon/py/pyutils.py
cornichon/vb/nunit.py
cornichon/vb/unittesting.py
cornichon/vb/vbscenarios.py
cornichon/vb/vbutils.py
cornichon-0.9.6.dist-info/LICENSE
cornichon-0.9.6.dist-info/METADATA
cornichon-0.9.6.dist-info/WHEEL
cornichon-0.9.6.dist-info/top_level.txt
cornichon-0.9.6.dist-info/RECORD
