Metadata-Version: 2.1
Name: cornichon
Version: 0.9.6
Summary: A small Gherkin DSL parser that generates stub code
Home-page: https://github.com/zebmason/Cornichon
Author: Zeb Mason
Author-email: consulting@cyclerouter.co.uk
Maintainer: Zeb Mason
Maintainer-email: consulting@cyclerouter.co.uk
License: LGPL v2
Platform: UNKNOWN
Classifier: Framework :: Pytest
Classifier: Topic :: Software Development :: Code Generators
Classifier: Topic :: Software Development :: Testing :: BDD
Classifier: Topic :: Text Processing
Classifier: Development Status :: 4 - Beta
Classifier: License :: OSI Approved :: GNU Lesser General Public License v2 (LGPLv2)
Classifier: Programming Language :: C#
Classifier: Programming Language :: C++
Classifier: Programming Language :: Python
Classifier: Programming Language :: Python :: 3
Classifier: Programming Language :: Visual Basic
Classifier: Operating System :: OS Independent
Classifier: Intended Audience :: Developers
Requires-Python: >=3.0.0
